calitp_data/__init__.py
calitp_data/config.py
calitp_data/storage.py
calitp_data/templates.py
calitp_data-2023.2.15.1.dist-info/WHEEL
calitp_data-2023.2.15.1.dist-info/METADATA
calitp_data-2023.2.15.1.dist-info/RECORD
